benchmark/__init__.py
benchmark/benchmark_api.py
benchmark/benchmarks.py
benchmark/dataset_api.py
benchmark/datasets.py
benchmark/grouping.py
benchmark/metadata.py
benchmark/metric_api.py
benchmark/metrics.py
benchmark/model_api.py
benchmark/models.py
benchmark/paths.py
benchmark/plot.py
benchmark/plotter_api.py
benchmark/plotters.py
benchmark/registry.py
benchmark/run.py
benchmark/sharding.py
benchmark/tag.py
gpflow/__init__.py
gpflow/base.py
gpflow/ci_utils.py
gpflow/functions.py
gpflow/keras.py
gpflow/kullback_leiblers.py
gpflow/logdensities.py
gpflow/mean_functions.py
gpflow/mypy_flags.py
gpflow/posteriors.py
gpflow/probability_distributions.py
gpflow/py.typed
gpflow/type_flags.py
gpflow/versions.py
gpflow/conditionals/__init__.py
gpflow/conditionals/conditionals.py
gpflow/conditionals/dispatch.py
gpflow/conditionals/sample_conditionals.py
gpflow/conditionals/uncertain_conditionals.py
gpflow/conditionals/util.py
gpflow/conditionals/multioutput/__init__.py
gpflow/conditionals/multioutput/conditionals.py
gpflow/conditionals/multioutput/sample_conditionals.py
gpflow/config/__config__.py
gpflow/config/__init__.py
gpflow/covariances/__init__.py
gpflow/covariances/dispatch.py
gpflow/covariances/kufs.py
gpflow/covariances/kuus.py
gpflow/covariances/multioutput/__init__.py
gpflow/covariances/multioutput/kufs.py
gpflow/covariances/multioutput/kuus.py
gpflow/expectations/__init__.py
gpflow/expectations/cross_kernels.py
gpflow/expectations/dispatch.py
gpflow/expectations/expectations.py
gpflow/expectations/linears.py
gpflow/expectations/mean_functions.py
gpflow/expectations/misc.py
gpflow/expectations/products.py
gpflow/expectations/quadratures.py
gpflow/expectations/squared_exponentials.py
gpflow/expectations/sums.py
gpflow/experimental/__init__.py
gpflow/experimental/utils.py
gpflow/inducing_variables/__init__.py
gpflow/inducing_variables/inducing_patch.py
gpflow/inducing_variables/inducing_variables.py
gpflow/inducing_variables/multioutput/__init__.py
gpflow-2.10.0.dist-info/LICENSE
gpflow-2.10.0.dist-info/METADATA
gpflow-2.10.0.dist-info/WHEEL
gpflow-2.10.0.dist-info/top_level.txt
gpflow-2.10.0.dist-info/RECORD
