Metadata-Version: 2.1
Name: gpflow
Version: 2.10.0
Summary: Gaussian process methods in TensorFlow
Home-page: https://www.gpflow.org
Author: James Hensman, Alex Matthews
Author-email: james.hensman@gmail.com
License: Apache License 2.0
Project-URL: Source on GitHub, https://github.com/GPflow/GPflow
Project-URL: Documentation, https://gpflow.github.io/GPflow/
Keywords: machine-learning gaussian-processes kernels tensorflow
Classifier: Development Status :: 5 - Production/Stable
Classifier: Environment :: GPU :: NVIDIA CUDA
Classifier: Intended Audience :: Developers
Classifier: Intended Audience :: Education
Classifier: Intended Audience :: Science/Research
Classifier: License :: OSI Approved :: Apache Software License
Classifier: Natural Language :: English
Classifier: Operating System :: MacOS :: MacOS X
Classifier: Operating System :: Microsoft :: Windows
Classifier: Operating System :: POSIX :: Linux
Classifier: Programming Language :: Python :: 3.7
Classifier: Programming Language :: Python :: 3.8
Classifier: Programming Language :: Python :: 3.9
Classifier: Programming Language :: Python :: 3.10
Classifier: Topic :: Scientific/Engineering :: Artificial Intelligence
Classifier: Typing :: Typed
Requires-Python: >=3.7
License-File: LICENSE
Requires-Dist: check-shapes (>=1.0.0)
Requires-Dist: deprecated
Requires-Dist: multipledispatch (>=0.6)
Requires-Dist: numpy (<2)
Requires-Dist: packaging
Requires-Dist: scipy
Requires-Dist: setuptools (>=41.0.0)
Requires-Dist: tabulate
Requires-Dist: tensorflow-probability[tf] (>=0.12.0)
Requires-Dist: typing-extensions
Requires-Dist: tensorflow (>=2.4.0) ; platform_system != "Darwin" or platform_machine != "arm64"
Requires-Dist: tensorflow-macos (>=2.4.0) ; platform_system == "Darwin" and platform_machine == "arm64"
Provides-Extra: imagetotensorboard
Requires-Dist: matplotlib ; extra == 'imagetotensorboard'
